srvdb-0.2.0.dist-info/METADATA
srvdb-0.2.0.dist-info/WHEEL
srvdb-0.2.0.dist-info/licenses/LICENSE
srvdb/__init__.py
srvdb/srvdb.cpython-311-darwin.so
srvdb-0.2.0.dist-info/RECORD
