Metadata-Version: 2.4
Name: srvdb
Version: 0.2.0
Classifier: Development Status :: 4 - Beta
Classifier: Intended Audience :: Developers
Classifier: License :: OSI Approved :: GNU Affero General Public License v3 or later (AGPLv3+)
Classifier: Programming Language :: Rust
Classifier: Programming Language :: Python :: 3
Classifier: Programming Language :: Python :: 3.8
Classifier: Programming Language :: Python :: 3.9
Classifier: Programming Language :: Python :: 3.10
Classifier: Programming Language :: Python :: 3.11
Classifier: Programming Language :: Python :: 3.12
Requires-Dist: numpy>=1.24.4
Requires-Dist: psutil>=7.2.0
Requires-Dist: scikit-learn>=1.3.2
License-File: LICENSE
Summary: Zero-Gravity Embedded Vector Database - Dynamic dimensions, RAM-efficient vector search
Keywords: vector,database,embedding,search,quantization
Author-email: Srinivas Nampalli <srinivas@example.com>
Requires-Python: >=3.8
Project-URL: Homepage, https://github.com/Srinivas26k/srvdb
Project-URL: Repository, https://github.com/Srinivas26k/srvdb
Project-URL: Documentation, https://github.com/Srinivas26k/srvdb/blob/main/README.md
